api_wrapper/__init__.py
api_wrapper/api_token.py
api_wrapper/api_wrapper.py
api_wrapper/apps.py
wrapper_42Portugal_test_name-1.0.0.dist-info/LICENSE
wrapper_42Portugal_test_name-1.0.0.dist-info/METADATA
wrapper_42Portugal_test_name-1.0.0.dist-info/WHEEL
wrapper_42Portugal_test_name-1.0.0.dist-info/top_level.txt
wrapper_42Portugal_test_name-1.0.0.dist-info/RECORD
