Metadata-Version: 2.1
Name: wrapper_42Portugal_test_name
Version: 1.0.0
Summary: A python package that simplifies the process of making API requests to 42 Portugal's API.
Author: 42 Portugal
License: MIT License
Project-URL: repository, https://github.com/mlanca-c/api-wrapper
Project-URL: Bug Tracker, https://github.com/mlanca-c/api-wrapper/issues
Classifier: Programming Language :: Python :: 3
Classifier: License :: OSI Approved :: MIT License
Classifier: Operating System :: OS Independent
Requires-Python: >=3.7
License-File: LICENSE
